knishioclient/__init__.py
knishioclient/client/__init__.py
knishioclient/exception/__init__.py
knishioclient/libraries/__init__.py
knishioclient/libraries/array.py
knishioclient/libraries/check.py
knishioclient/libraries/crypto.py
knishioclient/libraries/decimal.py
knishioclient/libraries/kem.py
knishioclient/libraries/strings.py
knishioclient/models/__init__.py
knishioclient/mutation/__init__.py
knishioclient/query/__init__.py
knishioclient/response/__init__.py
knishioclient-0.6.0.post1.dist-info/LICENSE
knishioclient-0.6.0.post1.dist-info/METADATA
knishioclient-0.6.0.post1.dist-info/WHEEL
knishioclient-0.6.0.post1.dist-info/top_level.txt
knishioclient-0.6.0.post1.dist-info/RECORD
