Metadata-Version: 2.2
Name: knishioclient
Version: 0.6.0.post1
Summary: Knish.IO Python API Client
Home-page: https://github.com/WishKnish/KnishIO-Client-Python
Author: Yuri Kizilov
Author-email: y.kizilov.sev@yandex.ru
License: LICENSE
Project-URL: Homepage, https://knish.io
Project-URL: GitHub: issues, https://github.com/WishKnish/KnishIO/issues
Project-URL: GitHub: wiki, https://github.com/WishKnish/KnishIO/wiki
Project-URL: GitHub: source, https://github.com/WishKnish/KnishIO
Project-URL: Docs, https://docs.knish.io
Keywords: wishknish,knishio,blockchain,dag,client
Platform: all
Classifier: Development Status :: 2 - Pre-Alpha
Classifier: License :: OSI Approved :: GNU General Public License v3 (GPLv3)
Classifier: Programming Language :: Python :: 3 :: Only
Classifier: Programming Language :: Python :: 3.11
Classifier: Programming Language :: Python :: 3.12
Classifier: Programming Language :: Python :: 3.13
Classifier: Topic :: Utilities
Requires-Python: >=3.6.0
License-File: LICENSE
Requires-Dist: libnacl>=2.1.0
Requires-Dist: numpy>=2.1.3
Requires-Dist: base58>=2.1.1
Requires-Dist: setuptools>=75.1.0
Requires-Dist: aiohttp>=3.11.11
Requires-Dist: cryptography>=44.0.0
Requires-Dist: pycryptodome>=3.21.0
Dynamic: author
Dynamic: author-email
Dynamic: classifier
Dynamic: description
Dynamic: description-content-type
Dynamic: home-page
Dynamic: keywords
Dynamic: license
Dynamic: platform
Dynamic: project-url
Dynamic: requires-dist
Dynamic: requires-python
Dynamic: summary
